{
  "type": "minecraft:block",
  "pools": [
    {
      "bonus_rolls": 0.0,
      "entries": [
        {
          "type": "minecraft:alternatives",
          "children": [
            {
              "type": "minecraft:item",
              "conditions": [
                {
                  "condition": "minecraft:match_tool",
                  "predicate": {
                    "enchantments": [
                      {
                        "enchantment": "minecraft:silk_touch",
                        "levels": {
                          "min": 1
                        }
                      }
                    ]
                  }
                }
              ],
              "name": "more_crustacean_whiteheket:jewellery_chest"
            }
          ]
        }
      ],
      "rolls": 1
    },
    {
      "rolls": 1,
      "entries": [
        {
          "type": "minecraft:item",
          "name": "more_crustacean_whiteheket:pearl"
        }
      ],
      "conditions": [
        {
          "condition": "minecraft:survives_explosion"
        },
        {
          "condition": "minecraft:inverted",
          "term": {
            "condition": "minecraft:any_of",
            "terms": [
              {
                "condition": "minecraft:match_tool",
                "predicate": {
                  "enchantments": [
                    {
                      "enchantment": "minecraft:silk_touch",
                      "levels": {
                        "min": 1
                      }
                    }
                  ]
                }
              }
            ]
          }
        }
      ]
    },
    {
      "rolls": 1,
      "entries": [
        {
          "type": "minecraft:item",
          "name": "minecraft:potion",
          "functions": [
            {
              "function": "minecraft:set_stew_effect",
              "effects": [
                {
                  "type": "minecraft:water_breathing",
                  "duration": 120000
                }
              ]
            }
          ]
        }
      ],
      "conditions": [
        {
          "condition": "minecraft:survives_explosion"
        },
        {
          "condition": "minecraft:inverted",
          "term": {
            "condition": "minecraft:any_of",
            "terms": [
              {
                "condition": "minecraft:match_tool",
                "predicate": {
                  "enchantments": [
                    {
                      "enchantment": "minecraft:silk_touch",
                      "levels": {
                        "min": 1
                      }
                    }
                  ]
                }
              }
            ]
          }
        }
      ]
    },
    {
      "rolls": 1,
      "entries": [
        {
          "type": "minecraft:item",
          "name": "minecraft:compass"
        }
      ],
      "conditions": [
        {
          "condition": "minecraft:survives_explosion"
        },
        {
          "condition": "minecraft:inverted",
          "term": {
            "condition": "minecraft:any_of",
            "terms": [
              {
                "condition": "minecraft:match_tool",
                "predicate": {
                  "enchantments": [
                    {
                      "enchantment": "minecraft:silk_touch",
                      "levels": {
                        "min": 1
                      }
                    }
                  ]
                }
              }
            ]
          }
        }
      ]
    },
    {
      "rolls": 1,
      "entries": [
        {
          "type": "minecraft:item",
          "name": "minecraft:iron_sword",
          "functions": [
            {
              "function": "minecraft:enchant_with_levels",
              "levels": 20
            }
          ]
        }
      ],
      "conditions": [
        {
          "condition": "minecraft:survives_explosion"
        },
        {
          "condition": "minecraft:inverted",
          "term": {
            "condition": "minecraft:any_of",
            "terms": [
              {
                "condition": "minecraft:match_tool",
                "predicate": {
                  "enchantments": [
                    {
                      "enchantment": "minecraft:silk_touch",
                      "levels": {
                        "min": 1
                      }
                    }
                  ]
                }
              }
            ]
          }
        }
      ]
    },
    {
      "rolls": 5,
      "bonus_rolls": 10,
      "entries": [
        {
          "type": "minecraft:item",
          "name": "minecraft:diamond",
          "weight": 1,
          "functions": [
            {
              "function": "minecraft:set_count",
              "count": 2
            }
          ]
        },
        {
          "type": "minecraft:item",
          "name": "minecraft:iron_ingot",
          "weight": 5,
          "functions": [
            {
              "function": "minecraft:set_count",
              "count": 5
            }
          ]
        },
        {
          "type": "minecraft:item",
          "name": "minecraft:gold_ingot",
          "weight": 5,
          "functions": [
            {
              "function": "minecraft:set_count",
              "count": 5
            }
          ]
        },
        {
          "type": "minecraft:item",
          "name": "minecraft:emerald",
          "weight": 30,
          "functions": [
            {
              "function": "minecraft:set_count",
              "count": 10
            }
          ]
        },
        {
          "type": "minecraft:item",
          "name": "minecraft:gold_nugget",
          "weight": 40,
          "functions": [
            {
              "function": "minecraft:set_count",
              "count": 8
            }
          ]
        },
        {
          "type": "minecraft:item",
          "name": "minecraft:iron_nugget",
          "weight": 40,
          "functions": [
            {
              "function": "minecraft:set_count",
              "count": 8
            }
          ]
        }
      ],
      "conditions": [
        {
          "condition": "minecraft:survives_explosion"
        },
        {
          "condition": "minecraft:inverted",
          "term": {
            "condition": "minecraft:any_of",
            "terms": [
              {
                "condition": "minecraft:match_tool",
                "predicate": {
                  "enchantments": [
                    {
                      "enchantment": "minecraft:silk_touch",
                      "levels": {
                        "min": 1
                      }
                    }
                  ]
                }
              }
            ]
          }
        }
      ]
    }
  ]
}